setup.py
hexview/__init__.py
hexview/colortheme.py
hexview/common.py
hexview/hexview.py
hexview/hexview.ui
hexview/hexview_auto.py
hexview/mutablenamedtuple.py
hexview/tablecellstylemodels.py
python_pyqt5_hexview.egg-info/PKG-INFO
python_pyqt5_hexview.egg-info/SOURCES.txt
python_pyqt5_hexview.egg-info/dependency_links.txt
python_pyqt5_hexview.egg-info/entry_points.txt
python_pyqt5_hexview.egg-info/requires.txt
python_pyqt5_hexview.egg-info/top_level.txt