Metadata-Version: 1.0
Name: python-pyqt5-hexview
Version: 0.4.2
Summary: PyQt5 hex viewer widget.
Home-page: https://github.com/williballenthin/python-pyqt5-hexview
Author: Willi Ballenthin
Author-email: willi.ballenthin@gmail.com
License: Apache 2.0 License
Platform: UNKNOWN
